yta_image/__init__.py
yta_image/background.py
yta_image/color/__init__.py
yta_image/color/picker.py
yta_image/converter.py
yta_image/description/__init__.py
yta_image/description/descriptor.py
yta_image/download/__init__.py
yta_image/download/youtube.py
yta_image/edition/__init__.py
yta_image/edition/editor.py
yta_image/edition/filter/__init__.py
yta_image/edition/filter/gameboy.py
yta_image/edition/filter/motion_blur.py
yta_image/edition/filter/pixelate.py
yta_image/edition/filter/sketch/__init__.py
yta_image/edition/filter/sketch/workers/__init__.py
yta_image/edition/filter/sketch/workers/filters.py
yta_image/edition/filter/sketch/workers/linedraw.py
yta_image/edition/filter/sketch/workers/perlin.py
yta_image/edition/filter/sketch/workers/strokesort.py
yta_image/edition/filter/sketch/workers/util.py
yta_image/edition/filter/sticker.py
yta_image/edition/settings.py
yta_image/experimental/__init__.py
yta_image/experimental/download/__init__.py
yta_image/experimental/download/bing.py
yta_image/experimental/download/image_searcher.py
yta_image/generation/__init__.py
yta_image/generation/ai/__init__.py
yta_image/generation/ai/generator.py
yta_image/generation/reviews/__init__.py
yta_image/generation/reviews/tripadvisor/__init__.py
yta_image/generation/reviews/tripadvisor/generator.py
yta_image/generation/rrss/__init__.py
yta_image/generation/rrss/discord/__init__.py
yta_image/generation/rrss/youtube/__init__.py
yta_image/greenscreen/__init__.py
yta_image/greenscreen/remover.py
yta_image/mask/__init__.py
yta_image/mask/presets.py
yta_image/parser.py
yta_image/processor.py
yta_image/region/__init__.py
yta_image/region/finder.py
yta_image/size.py
yta_image/validator.py
yta_image-0.0.16.dist-info/LICENSE
yta_image-0.0.16.dist-info/METADATA
yta_image-0.0.16.dist-info/WHEEL
yta_image-0.0.16.dist-info/RECORD
