Metadata-Version: 2.3
Name: yta-image
Version: 0.0.16
Summary: Youtube Autonomous Image Module.
Author: danialcala94
Author-email: danielalcalavalera@gmail.com
Requires-Python: ==3.9
Classifier: Programming Language :: Python :: 3
Classifier: Programming Language :: Python :: 3.9
